lampman/.git/objects/19/5d2459153beb12acbcdc379853657e9b84ab58
lampman/.git/objects/69/5e56c1fe805584eae34da34105ec3ebd282938
lampman/__main__.py
lampman/main.py
lampman-1.0.0.dist-info/entry_points.txt
lampman-1.0.0.dist-info/METADATA
lampman-1.0.0.dist-info/WHEEL
lampman-1.0.0.dist-info/RECORD
