Metadata-Version: 2.3
Name: lampman
Version: 1.0.0
Summary: MathLamp version manager
License: MIT
Author: RubberSpring
Author-email: 143825964+rafablog77@users.noreply.github.com
Requires-Python: >=3.13
Classifier: License :: OSI Approved :: MIT License
Classifier: Programming Language :: Python :: 3
Classifier: Programming Language :: Python :: 3.13
Requires-Dist: typer (>=0.20.0,<0.21.0)
Requires-Dist: virtualenv (>=20.35.4,<21.0.0)
